<?xml version="1.0" encoding="UTF-8"?>
<objects serializationModel="Studio.02.03.00">
	<object class="Event" id="{b9389b98-0fe8-4746-92f2-30820bccfb89}">
		<property name="name">
			<value>EnemyDamaged</value>
		</property>
		<property name="outputFormat">
			<value>1</value>
		</property>
		<relationship name="folder">
			<destination>{9720c8bb-6502-4a38-b597-d8a0ba59b698}</destination>
		</relationship>
		<relationship name="mixer">
			<destination>{f9e4382d-b8a1-4fbc-b9b8-4e04aa852b1d}</destination>
		</relationship>
		<relationship name="masterTrack">
			<destination>{eb9e8989-d2fd-4f5d-9c0f-442b034467d0}</destination>
		</relationship>
		<relationship name="mixerInput">
			<destination>{f69e53cd-097e-4254-8be9-c23da5e9a517}</destination>
		</relationship>
		<relationship name="automatableProperties">
			<destination>{c8b0b620-07bd-4408-a299-afe910ac561b}</destination>
		</relationship>
		<relationship name="markerTracks">
			<destination>{1e7e0abd-4746-4030-9848-65078bece01e}</destination>
		</relationship>
		<relationship name="groupTracks">
			<destination>{fdab042f-5129-4e74-8e69-b4baa26bc4d7}</destination>
			<destination>{3b9842f5-dec5-4d51-b6cb-6acf0f6c89e9}</destination>
		</relationship>
		<relationship name="timeline">
			<destination>{b7c6c181-5c6d-466a-b99b-2e1816315cbe}</destination>
		</relationship>
		<relationship name="banks">
			<destination>{7e45068f-1ba8-4ee0-bd08-ce295c512c4e}</destination>
		</relationship>
	</object>
	<object class="EventMixer" id="{f9e4382d-b8a1-4fbc-b9b8-4e04aa852b1d}">
		<relationship name="masterBus">
			<destination>{76aeaca7-67b1-4cc0-bd0f-85d1fcb6129c}</destination>
		</relationship>
	</object>
	<object class="MasterTrack" id="{eb9e8989-d2fd-4f5d-9c0f-442b034467d0}">
		<relationship name="mixerGroup">
			<destination>{76aeaca7-67b1-4cc0-bd0f-85d1fcb6129c}</destination>
		</relationship>
	</object>
	<object class="MixerInput" id="{f69e53cd-097e-4254-8be9-c23da5e9a517}">
		<relationship name="effectChain">
			<destination>{7e952ccb-4f4a-43b4-8f35-2d4a16fa81ff}</destination>
		</relationship>
		<relationship name="panner">
			<destination>{3bc29be0-427b-47e5-9536-2c9b03d07375}</destination>
		</relationship>
		<relationship name="output">
			<destination>{4f48b2c3-4093-424c-8078-734498caa92b}</destination>
		</relationship>
	</object>
	<object class="EventAutomatableProperties" id="{c8b0b620-07bd-4408-a299-afe910ac561b}" />
	<object class="MarkerTrack" id="{1e7e0abd-4746-4030-9848-65078bece01e}" />
	<object class="GroupTrack" id="{fdab042f-5129-4e74-8e69-b4baa26bc4d7}">
		<relationship name="modules">
			<destination>{a3417ef1-d19f-404c-8526-1dd02beb4df9}</destination>
		</relationship>
		<relationship name="mixerGroup">
			<destination>{abf51779-53ea-4faf-ad62-f139843d9fb7}</destination>
		</relationship>
	</object>
	<object class="GroupTrack" id="{3b9842f5-dec5-4d51-b6cb-6acf0f6c89e9}">
		<relationship name="modules">
			<destination>{b1804332-8220-41a3-b4a6-4cec5cb97722}</destination>
		</relationship>
		<relationship name="mixerGroup">
			<destination>{07ae3e11-797b-4a6a-a685-896c1db55890}</destination>
		</relationship>
	</object>
	<object class="Timeline" id="{b7c6c181-5c6d-466a-b99b-2e1816315cbe}">
		<relationship name="modules">
			<destination>{a3417ef1-d19f-404c-8526-1dd02beb4df9}</destination>
			<destination>{b1804332-8220-41a3-b4a6-4cec5cb97722}</destination>
		</relationship>
	</object>
	<object class="EventMixerMaster" id="{76aeaca7-67b1-4cc0-bd0f-85d1fcb6129c}">
		<property name="volume">
			<value>-10</value>
		</property>
		<relationship name="effectChain">
			<destination>{2a1e0b21-d012-492e-a789-c3c0b87d01d2}</destination>
		</relationship>
		<relationship name="panner">
			<destination>{82248135-3665-4a80-9d68-097a7ee8423b}</destination>
		</relationship>
		<relationship name="mixer">
			<destination>{f9e4382d-b8a1-4fbc-b9b8-4e04aa852b1d}</destination>
		</relationship>
	</object>
	<object class="MixerBusEffectChain" id="{7e952ccb-4f4a-43b4-8f35-2d4a16fa81ff}">
		<relationship name="effects">
			<destination>{d0c2b5e8-81ee-443a-893e-eb3a64cda128}</destination>
		</relationship>
	</object>
	<object class="MixerBusPanner" id="{3bc29be0-427b-47e5-9536-2c9b03d07375}" />
	<object class="MultiSound" id="{a3417ef1-d19f-404c-8526-1dd02beb4df9}">
		<property name="isAsync">
			<value>true</value>
		</property>
		<property name="length">
			<value>2.9273750000000001</value>
		</property>
		<property name="maxVoices">
			<value>3</value>
		</property>
		<property name="playlistMode">
			<value>1</value>
		</property>
		<relationship name="modulators">
			<destination>{4c3b687a-7d47-4a77-a593-ce08f37fbc08}</destination>
		</relationship>
		<relationship name="fadeInCurve">
			<destination>{b8ccc754-4cf5-40b3-8d4c-5dfa4d0e5124}</destination>
		</relationship>
		<relationship name="fadeOutCurve">
			<destination>{5cf18ad6-9d56-477b-9e9b-5bf679d27f8a}</destination>
		</relationship>
		<relationship name="sounds">
			<destination>{98cbe83a-1a2d-4f76-ac06-a0c6d4b2bd17}</destination>
			<destination>{24c3b38d-70be-41b8-a5f3-b4f70fd1cff2}</destination>
		</relationship>
	</object>
	<object class="EventMixerGroup" id="{abf51779-53ea-4faf-ad62-f139843d9fb7}">
		<property name="name">
			<value>Audio 1</value>
		</property>
		<relationship name="modulators">
			<destination>{8696b106-1bb6-4431-a2ca-6055601a3f27}</destination>
		</relationship>
		<relationship name="effectChain">
			<destination>{6c094630-ecae-4f4e-9b1c-afb1c860aa17}</destination>
		</relationship>
		<relationship name="panner">
			<destination>{ebb158d8-b9ed-4049-8656-44e5148328a7}</destination>
		</relationship>
		<relationship name="output">
			<destination>{76aeaca7-67b1-4cc0-bd0f-85d1fcb6129c}</destination>
		</relationship>
	</object>
	<object class="SingleSound" id="{b1804332-8220-41a3-b4a6-4cec5cb97722}">
		<property name="length">
			<value>0.37829166666666669</value>
		</property>
		<relationship name="modulators">
			<destination>{acc8c606-5adc-4d33-804c-8bda0ab6c16d}</destination>
		</relationship>
		<relationship name="audioFile">
			<destination>{4462abbc-8644-4f9d-9976-afad09ace58a}</destination>
		</relationship>
	</object>
	<object class="EventMixerGroup" id="{07ae3e11-797b-4a6a-a685-896c1db55890}">
		<property name="volume">
			<value>6</value>
		</property>
		<property name="name">
			<value>Audio 2</value>
		</property>
		<relationship name="effectChain">
			<destination>{a8a6fecf-ed6d-46e7-bef9-c89381cee967}</destination>
		</relationship>
		<relationship name="panner">
			<destination>{2a33388a-cc86-489c-a1fb-5d40afbebb0f}</destination>
		</relationship>
		<relationship name="output">
			<destination>{76aeaca7-67b1-4cc0-bd0f-85d1fcb6129c}</destination>
		</relationship>
	</object>
	<object class="MixerBusEffectChain" id="{2a1e0b21-d012-492e-a789-c3c0b87d01d2}">
		<relationship name="effects">
			<destination>{94046b46-195a-46e4-b349-865ef8edd7ae}</destination>
		</relationship>
	</object>
	<object class="MixerBusPanner" id="{82248135-3665-4a80-9d68-097a7ee8423b}" />
	<object class="MixerBusFader" id="{d0c2b5e8-81ee-443a-893e-eb3a64cda128}" />
	<object class="RandomizerModulator" id="{4c3b687a-7d47-4a77-a593-ce08f37fbc08}">
		<property name="nameOfPropertyBeingModulated">
			<value>pitch</value>
		</property>
		<property name="amount">
			<value>2.08333349</value>
		</property>
	</object>
	<object class="FadeCurve" id="{b8ccc754-4cf5-40b3-8d4c-5dfa4d0e5124}">
		<relationship name="startPoint">
			<destination>{00275066-32c4-4bf4-ab97-58d011481551}</destination>
		</relationship>
		<relationship name="endPoint">
			<destination>{e782c0c1-f062-4db9-804d-9a523ba7d1b0}</destination>
		</relationship>
	</object>
	<object class="FadeCurve" id="{5cf18ad6-9d56-477b-9e9b-5bf679d27f8a}">
		<relationship name="startPoint">
			<destination>{3ea1a7f0-87a5-4e83-9b33-87e93860e395}</destination>
		</relationship>
		<relationship name="endPoint">
			<destination>{fb279d3d-db5d-4554-96cb-24f03356cb97}</destination>
		</relationship>
	</object>
	<object class="SingleSound" id="{98cbe83a-1a2d-4f76-ac06-a0c6d4b2bd17}">
		<relationship name="audioFile">
			<destination>{93669c0a-0528-4e31-a69d-de5143da2634}</destination>
		</relationship>
	</object>
	<object class="SingleSound" id="{24c3b38d-70be-41b8-a5f3-b4f70fd1cff2}">
		<relationship name="audioFile">
			<destination>{4c323576-a04e-4239-ae6b-fcced57d9c86}</destination>
		</relationship>
	</object>
	<object class="RandomizerModulator" id="{8696b106-1bb6-4431-a2ca-6055601a3f27}">
		<property name="nameOfPropertyBeingModulated">
			<value>volume</value>
		</property>
		<property name="amount">
			<value>5</value>
		</property>
	</object>
	<object class="MixerBusEffectChain" id="{6c094630-ecae-4f4e-9b1c-afb1c860aa17}">
		<relationship name="effects">
			<destination>{97d0c7ee-66a1-4418-8ae5-cab040c27515}</destination>
			<destination>{752033fd-2d8c-410d-b792-b0bf888f93cc}</destination>
		</relationship>
	</object>
	<object class="MixerBusPanner" id="{ebb158d8-b9ed-4049-8656-44e5148328a7}" />
	<object class="RandomizerModulator" id="{acc8c606-5adc-4d33-804c-8bda0ab6c16d}">
		<property name="nameOfPropertyBeingModulated">
			<value>pitch</value>
		</property>
		<property name="amount">
			<value>4.16666698</value>
		</property>
	</object>
	<object class="MixerBusEffectChain" id="{a8a6fecf-ed6d-46e7-bef9-c89381cee967}">
		<relationship name="effects">
			<destination>{4223932e-7b80-4938-89c2-d415c6221463}</destination>
		</relationship>
	</object>
	<object class="MixerBusPanner" id="{2a33388a-cc86-489c-a1fb-5d40afbebb0f}" />
	<object class="MixerBusFader" id="{94046b46-195a-46e4-b349-865ef8edd7ae}" />
	<object class="AutomationPoint" id="{00275066-32c4-4bf4-ab97-58d011481551}">
		<property name="position">
			<value>0</value>
		</property>
		<property name="value">
			<value>0</value>
		</property>
		<property name="curveShape">
			<value>-0.2547189</value>
		</property>
	</object>
	<object class="AutomationPoint" id="{e782c0c1-f062-4db9-804d-9a523ba7d1b0}">
		<property name="position">
			<value>0</value>
		</property>
		<property name="value">
			<value>1</value>
		</property>
	</object>
	<object class="AutomationPoint" id="{3ea1a7f0-87a5-4e83-9b33-87e93860e395}">
		<property name="position">
			<value>0</value>
		</property>
		<property name="value">
			<value>1</value>
		</property>
		<property name="curveShape">
			<value>0.204003036</value>
		</property>
	</object>
	<object class="AutomationPoint" id="{fb279d3d-db5d-4554-96cb-24f03356cb97}">
		<property name="position">
			<value>2.9273750000000001</value>
		</property>
		<property name="value">
			<value>0</value>
		</property>
	</object>
	<object class="DistortionEffect" id="{97d0c7ee-66a1-4418-8ae5-cab040c27515}">
		<property name="level">
			<value>0.275000006</value>
		</property>
		<relationship name="modulators">
			<destination>{738c1212-bc6d-42fd-9320-dcdda212da1c}</destination>
		</relationship>
	</object>
	<object class="MixerBusFader" id="{752033fd-2d8c-410d-b792-b0bf888f93cc}" />
	<object class="MixerBusFader" id="{4223932e-7b80-4938-89c2-d415c6221463}" />
	<object class="RandomizerModulator" id="{738c1212-bc6d-42fd-9320-dcdda212da1c}">
		<property name="nameOfPropertyBeingModulated">
			<value>level</value>
		</property>
		<property name="amount">
			<value>24</value>
		</property>
	</object>
</objects>
